matinfwebapi/Api.py
matinfwebapi/__init__.py
crc165_api-0.1.5.dist-info/METADATA
crc165_api-0.1.5.dist-info/WHEEL
crc165_api-0.1.5.dist-info/top_level.txt
crc165_api-0.1.5.dist-info/RECORD
