Metadata-Version: 2.4
Name: crc165-api
Version: 0.1.5
Summary: Python wrapper for the CRC 1625 MatInf VRO API
Home-page: https://gitlab.ruhr-uni-bochum.de/icams-mids/crc1625rdmswrapper
Author: Doaa Mohamed
Author-email: Doaa Mohamed <doaamahmoud262@yahoo.com>
License-Expression: MIT
Project-URL: Homepage, https://pypi.org/project/crc165-api/
Project-URL: Source, https://gitlab.ruhr-uni-bochum.de/icams-mids/crc1625rdmswrapper
Project-URL: Tracker, https://gitlab.ruhr-uni-bochum.de/icams-mids/crc1625rdmswrapper/issues
Keywords: materials,FAIR,API,CRC165,data-management
Classifier: Programming Language :: Python :: 3
Classifier: Operating System :: OS Independent
Requires-Python: >=3.7
Requires-Dist: requests
Requires-Dist: pandas
Requires-Dist: openpyxl
Requires-Dist: scipy
Requires-Dist: numpy
Dynamic: author
Dynamic: home-page
Dynamic: requires-python
